{"debug":false,"default":false,"words":[{"word":"accept"},{"word":"add"},{"word":"admire"},{"word":"admit"},{"word":"advise"},{"word":"afford"},{"word":"agree"},{"word":"alert"},{"word":"allow"},{"word":"amuse"},{"word":"analyse"},{"word":"announce"},{"word":"annoy"},{"word":"answer"},{"word":"apologise"},{"word":"appear"},{"word":"applaud"},{"word":"appreciate"},{"word":"approve"},{"word":"argue"},{"word":"arrange"},{"word":"arrest"},{"word":"arrive"},{"word":"ask"},{"word":"attach"},{"word":"attack"},{"word":"attempt"},{"word":"attend"},{"word":"attract"},{"word":"avoid"},{"word":"back"},{"word":"bake"},{"word":"balance"},{"word":"ban"},{"word":"bang"},{"word":"bare"},{"word":"bat"},{"word":"bathe"},{"word":"battle"},{"word":"beam"},{"word":"beg"},{"word":"behave"},{"word":"belong"},{"word":"bleach"},{"word":"bless"},{"word":"blind"},{"word":"blink"},{"word":"blot"},{"word":"blush"},{"word":"boast"},{"word":"boil"},{"word":"bolt"},{"word":"bomb"},{"word":"book"},{"word":"bore"},{"word":"borrow"},{"word":"bounce"},{"word":"bow"},{"word":"box"},{"word":"brake"},{"word":"branch"},{"word":"breathe"},{"word":"bruise"},{"word":"brush"},{"word":"bubble"},{"word":"bump"},{"word":"burn"},{"word":"bury"},{"word":"buzz"},{"word":"calculate"},{"word":"call"},{"word":"camp"},{"word":"care"},{"word":"carry"},{"word":"carve"},{"word":"cause"},{"word":"challenge"},{"word":"change"},{"word":"charge"},{"word":"chase"},{"word":"cheat"},{"word":"check"},{"word":"cheer"},{"word":"chew"},{"word":"choke"},{"word":"chop"},{"word":"claim"},{"word":"clap"},{"word":"clean"},{"word":"clear"},{"word":"clip"},{"word":"close"},{"word":"coach"},{"word":"coil"},{"word":"collect"},{"word":"colour"},{"word":"comb"},{"word":"command"},{"word":"communicate"},{"word":"compare"},{"word":"compete"},{"word":"complain"},{"word":"complete"},{"word":"concentrate"},{"word":"concern"},{"word":"confess"},{"word":"confuse"},{"word":"connect"},{"word":"consider"},{"word":"consist"},{"word":"contain"},{"word":"continue"},{"word":"copy"},{"word":"correct"},{"word":"cough"},{"word":"count"},{"word":"cover"},{"word":"crack"},{"word":"crash"},{"word":"crawl"},{"word":"cross"},{"word":"crush"},{"word":"cry"},{"word":"cure"},{"word":"curl"},{"word":"curve"},{"word":"cycle"},{"word":"dam"},{"word":"damage"},{"word":"dance"},{"word":"dare"},{"word":"decay"},{"word":"deceive"},{"word":"decide"},{"word":"decorate"},{"word":"delay"},{"word":"delight"},{"word":"deliver"},{"word":"depend"},{"word":"describe"},{"word":"desert"},{"word":"deserve"},{"word":"destroy"},{"word":"detect"},{"word":"develop"},{"word":"disagree"},{"word":"disappear"},{"word":"disapprove"},{"word":"disarm"},{"word":"discover"},{"word":"dislike"},{"word":"divide"},{"word":"double"},{"word":"doubt"},{"word":"drag"},{"word":"drain"},{"word":"dream"},{"word":"dress"},{"word":"drip"},{"word":"drop"},{"word":"drown"},{"word":"drum"},{"word":"dry"},{"word":"dust"},{"word":"earn"},{"word":"educate"},{"word":"embarrass"},{"word":"employ"},{"word":"empty"},{"word":"encourage"},{"word":"end"},{"word":"enjoy"},{"word":"enter"},{"word":"entertain"},{"word":"escape"},{"word":"examine"},{"word":"excite"},{"word":"excuse"},{"word":"exercise"},{"word":"exist"},{"word":"expand"},{"word":"expect"},{"word":"explain"},{"word":"explode"},{"word":"extend"},{"word":"face"},{"word":"fade"},{"word":"fail"},{"word":"fancy"},{"word":"fasten"},{"word":"fax"},{"word":"fear"},{"word":"fence"},{"word":"fetch"},{"word":"file"},{"word":"fill"},{"word":"film"},{"word":"fire"},{"word":"fit"},{"word":"fix"},{"word":"flap"},{"word":"flash"},{"word":"float"},{"word":"flood"},{"word":"flow"},{"word":"flower"},{"word":"fold"},{"word":"follow"},{"word":"fool"},{"word":"force"},{"word":"form"},{"word":"found"},{"word":"frame"},{"word":"frighten"},{"word":"fry"},{"word":"gather"},{"word":"gaze"},{"word":"glow"},{"word":"glue"},{"word":"grab"},{"word":"grate"},{"word":"grease"},{"word":"greet"},{"word":"grin"},{"word":"grip"},{"word":"groan"},{"word":"guarantee"},{"word":"guard"},{"word":"guess"},{"word":"guide"},{"word":"hammer"},{"word":"hand"},{"word":"handle"},{"word":"hang"},{"word":"happen"},{"word":"harass"},{"word":"harm"},{"word":"hate"},{"word":"haunt"},{"word":"head"},{"word":"heal"},{"word":"heap"},{"word":"heat"},{"word":"help"},{"word":"hook"},{"word":"hop"},{"word":"hope"},{"word":"hover"},{"word":"hug"},{"word":"hum"},{"word":"hunt"},{"word":"hurry"},{"word":"identify"},{"word":"ignore"},{"word":"imagine"},{"word":"impress"},{"word":"improve"},{"word":"include"},{"word":"increase"},{"word":"influence"},{"word":"inform"},{"word":"inject"},{"word":"injure"},{"word":"instruct"},{"word":"intend"},{"word":"interest"},{"word":"interfere"},{"word":"interrupt"},{"word":"introduce"},{"word":"invent"},{"word":"invite"},{"word":"irritate"},{"word":"itch"},{"word":"jail"},{"word":"jam"},{"word":"jog"},{"word":"join"},{"word":"joke"},{"word":"judge"},{"word":"juggle"},{"word":"jump"},{"word":"kick"},{"word":"kill"},{"word":"kiss"},{"word":"kneel"},{"word":"knit"},{"word":"knock"},{"word":"knot"},{"word":"label"},{"word":"land"},{"word":"last"},{"word":"laugh"},{"word":"launch"},{"word":"learn"},{"word":"level"},{"word":"license"},{"word":"lick"},{"word":"lie"},{"word":"lighten"},{"word":"like"},{"word":"list"},{"word":"listen"},{"word":"live"},{"word":"load"},{"word":"lock"},{"word":"long"},{"word":"look"},{"word":"love"},{"word":"man"},{"word":"manage"},{"word":"march"},{"word":"mark"},{"word":"marry"},{"word":"match"},{"word":"mate"},{"word":"matter"},{"word":"measure"},{"word":"meddle"},{"word":"melt"},{"word":"memorise"},{"word":"mend"},{"word":"mess up"},{"word":"milk"},{"word":"mine"},{"word":"miss"},{"word":"mix"},{"word":"moan"},{"word":"moor"},{"word":"mourn"},{"word":"move"},{"word":"muddle"},{"word":"mug"},{"word":"multiply"},{"word":"murder"},{"word":"nail"},{"word":"name"},{"word":"need"},{"word":"nest"},{"word":"nod"},{"word":"note"},{"word":"notice"},{"word":"number"},{"word":"obey"},{"word":"object"},{"word":"observe"},{"word":"obtain"},{"word":"occur"},{"word":"offend"},{"word":"offer"},{"word":"open"},{"word":"order"},{"word":"overflow"},{"word":"owe"},{"word":"own"},{"word":"pack"},{"word":"paddle"},{"word":"paint"},{"word":"park"},{"word":"part"},{"word":"pass"},{"word":"paste"},{"word":"pat"},{"word":"pause"},{"word":"peck"},{"word":"pedal"},{"word":"peel"},{"word":"peep"},{"word":"perform"},{"word":"permit"},{"word":"phone"},{"word":"pick"},{"word":"pinch"},{"word":"pine"},{"word":"place"},{"word":"plan"},{"word":"plant"},{"word":"play"},{"word":"please"},{"word":"plug"},{"word":"point"},{"word":"poke"},{"word":"polish"},{"word":"pop"},{"word":"possess"},{"word":"post"},{"word":"pour"},{"word":"practise"},{"word":"pray"},{"word":"preach"},{"word":"precede"},{"word":"prefer"},{"word":"prepare"},{"word":"present"},{"word":"preserve"},{"word":"press"},{"word":"pretend"},{"word":"prevent"},{"word":"prick"},{"word":"print"},{"word":"produce"},{"word":"program"},{"word":"promise"},{"word":"protect"},{"word":"provide"},{"word":"pull"},{"word":"pump"},{"word":"punch"},{"word":"puncture"},{"word":"punish"},{"word":"push"},{"word":"question"},{"word":"queue"},{"word":"race"},{"word":"radiate"},{"word":"rain"},{"word":"raise"},{"word":"reach"},{"word":"realise"},{"word":"receive"},{"word":"recognise"},{"word":"record"},{"word":"reduce"},{"word":"reflect"},{"word":"refuse"},{"word":"regret"},{"word":"reign"},{"word":"reject"},{"word":"rejoice"},{"word":"relax"},{"word":"release"},{"word":"rely"},{"word":"remain"},{"word":"remember"},{"word":"remind"},{"word":"remove"},{"word":"repair"},{"word":"repeat"},{"word":"replace"},{"word":"reply"},{"word":"report"},{"word":"reproduce"},{"word":"request"},{"word":"rescue"},{"word":"retire"},{"word":"return"},{"word":"rhyme"},{"word":"rinse"},{"word":"risk"},{"word":"rob"},{"word":"rock"},{"word":"roll"},{"word":"rot"},{"word":"rub"},{"word":"ruin"},{"word":"rule"},{"word":"rush"},{"word":"sack"},{"word":"sail"},{"word":"satisfy"},{"word":"save"},{"word":"saw"},{"word":"scare"},{"word":"scatter"},{"word":"scold"},{"word":"scorch"},{"word":"scrape"},{"word":"scratch"},{"word":"scream"},{"word":"screw"},{"word":"scribble"},{"word":"scrub"},{"word":"seal"},{"word":"search"},{"word":"separate"},{"word":"serve"},{"word":"settle"},{"word":"shade"},{"word":"share"},{"word":"shave"},{"word":"shelter"},{"word":"shiver"},{"word":"shock"},{"word":"shop"},{"word":"shrug"},{"word":"sigh"},{"word":"sign"},{"word":"signal"},{"word":"sin"},{"word":"sip"},{"word":"ski"},{"word":"skip"},{"word":"slap"},{"word":"slip"},{"word":"slow"},{"word":"smash"},{"word":"smell"},{"word":"smile"},{"word":"smoke"},{"word":"snatch"},{"word":"sneeze"},{"word":"sniff"},{"word":"snore"},{"word":"snow"},{"word":"soak"},{"word":"soothe"},{"word":"sound"},{"word":"spare"},{"word":"spark"},{"word":"sparkle"},{"word":"spell"},{"word":"spill"},{"word":"spoil"},{"word":"spot"},{"word":"spray"},{"word":"sprout"},{"word":"squash"},{"word":"squeak"},{"word":"squeal"},{"word":"squeeze"},{"word":"stain"},{"word":"stamp"},{"word":"stare"},{"word":"start"},{"word":"stay"},{"word":"steer"},{"word":"step"},{"word":"stir"},{"word":"stitch"},{"word":"stop"},{"word":"store"},{"word":"strap"},{"word":"strengthen"},{"word":"stretch"},{"word":"strip"},{"word":"stroke"},{"word":"stuff"},{"word":"subtract"},{"word":"succeed"},{"word":"suck"},{"word":"suffer"},{"word":"suggest"},{"word":"suit"},{"word":"supply"},{"word":"support"},{"word":"suppose"},{"word":"surprise"},{"word":"surround"},{"word":"suspect"},{"word":"suspend"},{"word":"switch"},{"word":"talk"},{"word":"tame"},{"word":"tap"},{"word":"taste"},{"word":"tease"},{"word":"telephone"},{"word":"tempt"},{"word":"terrify"},{"word":"test"},{"word":"thank"},{"word":"thaw"},{"word":"tick"},{"word":"tickle"},{"word":"tie"},{"word":"time"},{"word":"tip"},{"word":"tire"},{"word":"touch"},{"word":"tour"},{"word":"tow"},{"word":"trace"},{"word":"trade"},{"word":"train"},{"word":"transport"},{"word":"trap"},{"word":"travel"},{"word":"treat"},{"word":"tremble"},{"word":"trick"},{"word":"trip"},{"word":"trot"},{"word":"trouble"},{"word":"trust"},{"word":"try"},{"word":"tug"},{"word":"tumble"},{"word":"turn"},{"word":"twist"},{"word":"type"},{"word":"undress"},{"word":"unfasten"},{"word":"unite"},{"word":"unlock"},{"word":"unpack"},{"word":"untidy"},{"word":"use"},{"word":"vanish"},{"word":"visit"},{"word":"wail"},{"word":"wait"},{"word":"walk"},{"word":"wander"},{"word":"want"},{"word":"warm"},{"word":"warn"},{"word":"wash"},{"word":"waste"},{"word":"watch"},{"word":"water"},{"word":"wave"},{"word":"weigh"},{"word":"welcome"},{"word":"whine"},{"word":"whip"},{"word":"whirl"},{"word":"whisper"},{"word":"whistle"},{"word":"wink"},{"word":"wipe"},{"word":"wish"},{"word":"wobble"},{"word":"wonder"},{"word":"work"},{"word":"worry"},{"word":"wrap"},{"word":"wreck"},{"word":"wrestle"},{"word":"wriggle"},{"word":"x-ray"},{"word":"yawn"},{"word":"yell"},{"word":"zip"},{"word":"zoom"}]}